enums.py
test_enums.py
enums.py-0.3.1.dist-info/LICENSE
enums.py-0.3.1.dist-info/METADATA
enums.py-0.3.1.dist-info/WHEEL
enums.py-0.3.1.dist-info/top_level.txt
enums.py-0.3.1.dist-info/RECORD
