Metadata-Version: 2.1
Name: enums.py
Version: 0.3.1
Summary: Enhanced Enum Implementation for Python
Home-page: https://github.com/nekitdev/enums.py
Author: nekitdev
Author-email: nekitdevofficial@gmail.com
License: MIT
Project-URL: Issue tracker, https://github.com/nekitdev/enums.py/issues
Platform: UNKNOWN
Classifier: Development Status :: 4 - Beta
Classifier: License :: OSI Approved :: MIT License
Classifier: Programming Language :: Python :: 3.6
Classifier: Programming Language :: Python :: 3.7
Classifier: Programming Language :: Python :: 3.8
Classifier: Programming Language :: Python :: 3.9
Classifier: Natural Language :: English
Classifier: Operating System :: OS Independent
Requires-Python: >=3.6
Provides-Extra: test
Requires-Dist: coverage ; extra == 'test'
Requires-Dist: flake8 ; extra == 'test'
Requires-Dist: pytest ; extra == 'test'
